<?xml version="1.0" encoding="UTF-8"?>
<Root>
  <GEOMETRY_INFO>
    <NUMBER_OF_TYPES>1</NUMBER_OF_TYPES>
    <NUMBER_OF_ATOMS>2</NUMBER_OF_ATOMS>
    <BRAVAIS_LATTICE_INDEX>4</BRAVAIS_LATTICE_INDEX>
    <SPIN_COMPONENTS>1</SPIN_COMPONENTS>
    <CELL_DIMENSIONS>
   6.093687070000000E+00   0.000000000000000E+00   1.546365030000000E+00
   0.000000000000000E+00   0.000000000000000E+00   0.000000000000000E+00
    </CELL_DIMENSIONS>
    <AT>
   1.000000000000000E+00   0.000000000000000E+00   0.000000000000000E+00
  -5.000000000000000E-01   8.660254037844999E-01   0.000000000000000E+00
   0.000000000000000E+00   0.000000000000000E+00   1.546365030000000E+00
    </AT>
    <BG>
   1.000000000000000E+00   5.773502691895849E-01  -0.000000000000000E+00
   0.000000000000000E+00   1.154700538379170E+00   0.000000000000000E+00
   0.000000000000000E+00  -0.000000000000000E+00   6.466778416477770E-01
    </BG>
    <UNIT_CELL_VOLUME_AU>303.02823464859011</UNIT_CELL_VOLUME_AU>
    <TYPE_NAME.1>Sc</TYPE_NAME.1>
    <MASS.1>44.595999999999997</MASS.1>
    <ATOM.1 SPECIES="Sc" INDEX="1" TAU="0.0000000000000000 0.0000000000000000 0.0000000000000000"/>
    <ATOM.2 SPECIES="Sc" INDEX="1" TAU="0.50000000000050004 0.28867513459454475 0.77318251500000001"/>
    <NUMBER_OF_Q>2</NUMBER_OF_Q>
  </GEOMETRY_INFO>
  <DIELECTRIC_PROPERTIES epsil="false" zstar="false" raman="false">
  </DIELECTRIC_PROPERTIES>
  <DYNAMICAL_MAT_.1>
    <Q_POINT>
   3.333333333333333E-01   5.773502691895848E-01   0.000000000000000E+00
    </Q_POINT>
    <PHI.1.1>
   1.287916219532629E-01   0.000000000000000E+00
   0.000000000000000E+00   2.597953095279980E-02
   0.000000000000000E+00  -1.037880183000967E-35
   0.000000000000000E+00  -2.597953095279980E-02
   1.287916219532447E-01   0.000000000000000E+00
   0.000000000000000E+00   5.992204030421441E-36
   0.000000000000000E+00   1.037880183000967E-35
   0.000000000000000E+00  -5.992204030421440E-36
   1.105782656149614E-01   0.000000000000000E+00
    </PHI.1.1>
    <PHI.1.2>
  -1.562137411971145E-03   2.705701365938179E-03
  -2.705701365937987E-03  -1.562137411971034E-03
   1.297350228751209E-36  -2.594700457502418E-36
  -2.705701365937987E-03  -1.562137411971034E-03
   1.562137411970923E-03  -2.705701365937794E-03
   7.490255038026801E-37  -4.494153022816080E-36
   2.594700457502418E-36   2.594700457502418E-36
   1.498051007605360E-36   9.362818797533501E-36
  -1.208274491725709E-30  -2.093418916740077E-30
    </PHI.1.2>
    <PHI.2.1>
  -1.562137411971145E-03  -2.705701365938179E-03
  -2.705701365937987E-03   1.562137411971034E-03
  -1.297350228751209E-36  -2.594700457502418E-36
  -2.705701365937987E-03   1.562137411971034E-03
   1.562137411970923E-03   2.705701365937794E-03
  -7.490255038026801E-37  -4.494153022816080E-36
  -2.594700457502418E-36   2.594700457502418E-36
  -1.498051007605360E-36   9.362818797533501E-36
  -1.208274491725709E-30   2.093418916740077E-30
    </PHI.2.1>
    <PHI.2.2>
   1.287916219532629E-01   0.000000000000000E+00
   0.000000000000000E+00  -2.597953095279980E-02
   0.000000000000000E+00  -1.037880183000967E-35
   0.000000000000000E+00   2.597953095279980E-02
   1.287916219532447E-01   0.000000000000000E+00
   0.000000000000000E+00   5.992204030421441E-36
   0.000000000000000E+00   1.037880183000967E-35
   0.000000000000000E+00  -5.992204030421440E-36
   1.105782656149614E-01   0.000000000000000E+00
    </PHI.2.2>
  </DYNAMICAL_MAT_.1>
  <DYNAMICAL_MAT_.2>
    <Q_POINT>
  -3.333333333333333E-01  -5.773502691895848E-01   0.000000000000000E+00
    </Q_POINT>
    <PHI.1.1>
   1.287916219532629E-01   0.000000000000000E+00
   2.775557561562891E-17  -2.597953095279980E-02
   0.000000000000000E+00   1.037880183000967E-35
   2.775557561562891E-17   2.597953095279980E-02
   1.287916219532446E-01   0.000000000000000E+00
   0.000000000000000E+00  -5.992204030421441E-36
   0.000000000000000E+00  -1.037880183000967E-35
  -2.396881612168576E-35   5.992204030421440E-36
   1.105782656149614E-01   0.000000000000000E+00
    </PHI.1.1>
    <PHI.1.2>
  -1.562137411971145E-03  -2.705701365938179E-03
  -2.705701365937987E-03   1.562137411971034E-03
   2.594700457502418E-36  -3.892050686253628E-36
  -2.705701365937987E-03   1.562137411971034E-03
   1.562137411970923E-03   2.705701365937794E-03
  -1.498051007605360E-36   7.490255038026799E-37
   5.189400915004837E-36  -2.594700457502418E-36
   2.996102015210720E-36  -4.494153022816080E-36
  -1.208220797796379E-30   2.093150447093425E-30
    </PHI.1.2>
    <PHI.2.1>
  -1.562137411971145E-03   2.705701365938179E-03
  -2.705701365937987E-03  -1.562137411971034E-03
  -2.594700457502418E-36  -3.892050686253628E-36
  -2.705701365937987E-03  -1.562137411971034E-03
   1.562137411970923E-03  -2.705701365937794E-03
   1.498051007605360E-36   7.490255038026799E-37
  -5.189400915004837E-36  -2.594700457502418E-36
  -2.996102015210720E-36  -4.494153022816080E-36
  -1.208220797796379E-30  -2.093150447093425E-30
    </PHI.2.1>
    <PHI.2.2>
   1.287916219532629E-01   0.000000000000000E+00
   2.775557561562891E-17   2.597953095279980E-02
   0.000000000000000E+00   1.037880183000967E-35
   2.775557561562891E-17  -2.597953095279980E-02
   1.287916219532446E-01   0.000000000000000E+00
   0.000000000000000E+00  -5.992204030421441E-36
   0.000000000000000E+00  -1.037880183000967E-35
   2.396881612168576E-35   5.992204030421440E-36
   1.105782656149614E-01   0.000000000000000E+00
    </PHI.2.2>
  </DYNAMICAL_MAT_.2>
  <FREQUENCIES_THZ_CMM1>
    <OMEGA.1>
   5.232197452315971E+00   1.745273209079853E+02
    </OMEGA.1>
    <DISPLACEMENT.1>
   5.9039803738559556E-002  -5.3671119159739621E-002
  -5.3671119159774766E-002  -5.9039803738552790E-002
  -1.4010053295021305E-015   3.5977115643070823E-015
  -1.5224224641782567E-003 -0.70258906536631904     
  0.70258906536656784       -1.5224224641755132E-003
   0.0000000000000000        0.0000000000000000     
    </DISPLACEMENT.1>
    <OMEGA.2>
   5.232197452315972E+00   1.745273209079854E+02
    </OMEGA.2>
    <DISPLACEMENT.2>
 -0.58858435119104702       0.38366935514253692     
  0.38366935514267064       0.58858435119125896     
  -6.6253410416702209E-017   2.0264472659944693E-016
   1.2551087906806811E-002  -7.8795670247169214E-002
   7.8795670247211985E-002   1.2551087906782216E-002
   0.0000000000000000        0.0000000000000000     
    </DISPLACEMENT.2>
    <OMEGA.3>
   5.426213980252690E+00   1.809990156674552E+02
    </OMEGA.3>
    <DISPLACEMENT.3>
   5.8980598183211417E-017  -2.0816681711721678E-016
  -8.1532003370909896E-017  -1.0061396160665477E-016
  0.50000000000181366      -0.86602540378339155     
   4.6416612707884197E-016  -3.1918911957973239E-015
   2.5049406993105083E-015   3.1844737058317332E-016
   0.0000000000000000        0.0000000000000000     
    </DISPLACEMENT.3>
    <OMEGA.4>
   5.426213980252690E+00   1.809990156674552E+02
    </OMEGA.4>
    <DISPLACEMENT.4>
   0.0000000000000000        0.0000000000000000     
   0.0000000000000000        0.0000000000000000     
   0.0000000000000000        0.0000000000000000     
   0.0000000000000000        0.0000000000000000     
   0.0000000000000000        0.0000000000000000     
   1.0000000000000000        0.0000000000000000     
    </DISPLACEMENT.4>
    <OMEGA.5>
   6.288662757609003E+00   2.097672102748163E+02
    </OMEGA.5>
    <DISPLACEMENT.5>
  0.43301270189178354       0.25000000000095579     
 -0.25000000000085548       0.43301270189160956     
   3.9425113293895039E-017  -3.5774777230630541E-016
   1.5543396738595574E-015  0.50000000000010025     
  0.49999999999989980       -1.4793767684324255E-015
   0.0000000000000000        0.0000000000000000     
    </DISPLACEMENT.5>
    <OMEGA.6>
   6.547892474045749E+00   2.184141828559860E+02
    </OMEGA.6>
    <DISPLACEMENT.6>
  0.43301270189176222       0.25000000000094563     
 -0.25000000000086853       0.43301270189162855     
  -2.2204460492503126E-016   1.9428902930940235E-016
   4.8281027266407932E-016 -0.50000000000007772     
 -0.49999999999992278       -2.2397881062109002E-016
   0.0000000000000000        0.0000000000000000     
    </DISPLACEMENT.6>
  </FREQUENCIES_THZ_CMM1>
</Root>
